autofunc/__init__.py
autofunc/lib.py
argrecurse-0.0.2.dist-info/LICENSE
argrecurse-0.0.2.dist-info/METADATA
argrecurse-0.0.2.dist-info/WHEEL
argrecurse-0.0.2.dist-info/top_level.txt
argrecurse-0.0.2.dist-info/RECORD
